Metadata-Version: 1.0
Name: py-distrib
Version: 0.1
Summary: Gaussian distributions
Home-page: UNKNOWN
Author: Kavii Suri
Author-email: surikavii@gmail.com
License: UNKNOWN
Platform: UNKNOWN
